{"distinct_id":"019f4278-51f1-70e0-ac93-87e7214fbe8c","event":"depthai_device_constructor","properties":{"$lib":"depthai-core","$lib_version":"3.7.1","$process_person_profile":false,"$session_id":"019f4277-e865-7ff4-8d91-3df43f96a151","device_id":"019f4278-5171-7b74-aa53-e79b100d1122","device_model":"oak-d-pro-poe-af","device_os_version":"","platform":"rvc2","protocol":"ethernet","protocol_speed":"unknown","source_component":"depthai-core","source_product":"depthai","standalone":false},"timestamp":"2026-07-08T16:03:29.394Z","uuid":"48069655-8580-4bf0-9c56-44658b29ce5e"}